{
  "$schema": "../../assetlist.schema.json",
  "chainName": "zigchaintestnet",
  "assets": [
    {
      "description": "The native token of ZIGChain",
      "denomUnits": [
        {
          "denom": "uzig",
          "exponent": 0,
          "aliases": [
            "microzig"
          ]
        },
        {
          "denom": "mzig",
          "exponent": 3,
          "aliases": [
            "millizig"
          ]
        },
        {
          "denom": "zig",
          "exponent": 6
        }
      ],
      "base": "uzig",
      "name": "ZIG",
      "display": "zig",
      "symbol": "ZIG",
      "coingeckoId": "zignaly",
      "assetType": "sdk.coin"
    }
  ]
}