{
  "$schema": "../chain.schema.json",
  "chainName": "bluechip",
  "status": "live",
  "website": "https://www.bluechip.link",
  "networkType": "mainnet",
  "prettyName": "BlueChip",
  "chainType": "cosmos",
  "chainId": "bluechip-1",
  "bech32Prefix": "bcp",
  "daemonName": "bluechipd",
  "nodeHome": "$HOME/.bluechip",
  "slip44": 118,
  "keyAlgos": [
    "secp256k1"
  ],
  "fees": {
    "feeTokens": [
      {
        "denom": "ubluechip",
        "fixedMinGasPrice": 0,
        "lowGasPrice": 0,
        "averageGasPrice": 0.025,
        "highGasPrice": 0.04
      }
    ]
  },
  "staking": {
    "stakingTokens": [
      {
        "denom": "ubluechip"
      }
    ]
  },
  "description": "Stake to the BlueChip chain, interact with the creator pools, and subscribe through the creator subscription contracts.",
  "codebase": {
    "gitRepo": "https://github.com/Bluechip23/bluechip/tree/main",
    "recommendedVersion": "v1",
    "compatibleVersions": [
      "v1"
    ],
    "cosmosSdkVersion": "0.46.7",
    "cosmwasmEnabled": true,
    "genesis": {
      "genesisUrl": "https://github.com/Bluechip23/bluechip/blob/main/genesis.json"
    },
    "versions": [
      {
        "name": "v1",
        "recommendedVersion": "v1",
        "compatibleVersions": [
          "v1"
        ],
        "cosmosSdkVersion": "0.46.7",
        "cosmwasmEnabled": true
      }
    ]
  },
  "peers": {
    "seeds": [

    ],
    "persistentPeers": [
      {
        "id": "3x4pynlp86prhcmtns742kgsgu7pjtzjpk8d93",
        "address": "http://67.28.8.88:26659/",
        "provider": "CryptoDungeon"
      }
    ]
  },
  "images": [
    {
      "png": "https://raw.githubusercontent.com/cosmos/chain-registry/master/bluechip/images/bluechip.png",
      "theme": {
        "primaryColorHex": "#0c94d3"
      }
    }
  ]
}