{
  "$schema": "../chain.schema.json",
  "chainName": "manifest",
  "networkType": "mainnet",
  "website": "https://manifestai.org/",
  "prettyName": "Manifest",
  "chainId": "manifest-ledger-mainnet",
  "chainType": "cosmos",
  "bech32Prefix": "manifest",
  "slip44": 118,
  "fees": {
    "feeTokens": [
      {
        "denom": "umfx",
        "fixedMinGasPrice": 0.05,
        "lowGasPrice": 0.5,
        "averageGasPrice": 1,
        "highGasPrice": 5
      }
    ]
  },
  "staking": {
    "stakingTokens": [
      {
        "denom": "upoa"
      }
    ]
  },
  "codebase": {

  },
  "apis": {
    "rpc": [
      {
        "address": "https://nodes.liftedinit.app/manifest/rpc"
      },
      {
        "address": "https://manifest-rpc.liftedinit.app"
      }
    ],
    "rest": [
      {
        "address": "https://nodes.liftedinit.app/manifest/api"
      },
      {
        "address": "https://manifest-rest.liftedinit.app"
      }
    ],
    "grpc": [
      {
        "address": "https://manifest-grpc.liftedinit.app"
      }
    ]
  },
  "explorers": [
    {
      "kind": "Default Explorer",
      "url": "https://manifest.explorers.guru/",
      "txPage": "https://manifest.explorers.guru/transactions"
    }
  ],
  "images": [
    {
      "imageSync": {
        "chainName": "manifest"
      },
      "png": "https://raw.githubusercontent.com/cosmos/chain-registry/master/manifest/images/manifest.png",
      "svg": "https://raw.githubusercontent.com/cosmos/chain-registry/master/manifest/images/manifest.svg",
      "theme": {
        "primaryColorHex": "#A087FF"
      }
    }
  ]
}